{ "_id" : "calendar", "n" : { "ru" : "Приближающиеся даты календаря" } }
{ "_id" : "comment", "n" : { "ru" : "Комментарии к моим событиям" } }
{ "_id" : "friend", "n" : { "ru" : "Запрос на дружбу" } }
{ "_id" : "invite", "n" : { "ru" : "Приглашение" } }
{ "_id" : "personal", "n" : { "ru" : "Личные сообщения" } }
{ "_id" : "present", "n" : { "ru" : "Получение подарка" } }
{ "_id" : "all", "n" : { "ru" : "Оповещать обо всех событиях" } }
{ "_id" : "subscription", "n" : { "ru" : "Мои подписки" } }
